{"capture_session_id":"capture-903acdab17964022869a3b383930b076","compression":"zstd","first_receive_at":"2026-07-23T09:00:01.339158Z","first_record_ordinal":0,"last_receive_at":"2026-07-23T09:48:49.245806Z","last_record_ordinal":3061,"manifest_sha256":"sha256:10889a20382dda5d92fb111757d295df3428f28fb4fb8cd3fee00e96a58105fd","manifest_version":"v0","object_path":"raw/source=polymarket/stream=market/date=2026-07-23/hour=09/95dfa6581245ab1b546862ced66e0d7a39c1d18a126cadf5605816d05057f32f.jsonl.zst","object_sha256":"sha256:95dfa6581245ab1b546862ced66e0d7a39c1d18a126cadf5605816d05057f32f","object_size_bytes":506513,"partition_date":"2026-07-23","partition_hour":"09","record_count":3062,"record_encoding":"canonical-json-lines-v0","sealed_at":"2026-07-23T09:48:51.573731Z","source":"polymarket","stream":"market"}
